clib/__init__.py
clib/cli/__init__.py
clib/cli/aliased_group.py
clib/cli/core.py
clib-0.0.1.dist-info/LICENSE
clib-0.0.1.dist-info/METADATA
clib-0.0.1.dist-info/WHEEL
clib-0.0.1.dist-info/entry_points.txt
clib-0.0.1.dist-info/top_level.txt
clib-0.0.1.dist-info/RECORD
