Metadata-Version: 2.1
Name: clib
Version: 0.0.1
Summary: A command line base to help build CLIs faster.
Home-page: https://gitlab.com/iwaseatenbyagrue/clib
Author: eatenbyagrue
Author-email: iwaseatenbyagrue@gmail.com
License: UNKNOWN
Platform: UNKNOWN
Requires-Dist: click
Requires-Dist: click-plugins
